{
    "name": "GIRA Repo",
    "identifier": "com.gira",
    "sourceURL": "https://provenance-emu.com/apps.json",
    "iconURL": "https://gocciolafr.github.io/gira/logo.jpg",
    "subtitle": "Una vasta collezione di app utili per il tuo iDevice!",
    "description": "Con GIRA potete esplorare un sacco di file IPA molto utili per il vostro iDevice! Esplora qui una vasta gamma di app gratuite come Spotify craccato, giochi non più disponibili e altro!\nCanale Telegram: https://t.me/girarepo",
    "website": "https://gocciolafr.github.io/gira",
    "tintColor": "#6b89a5",
    "featuredApps": [
        "com.spotify.client"
    ],
    
    "apps": [
        {
            "name": "Eevee Spotify",
            "bundleIdentifier": "com.spotify.client",
            "developerName": "asdfzxcvbn",
            "subtitle": "A tweak to get Spotify Premium for free, just like Spotilife",
            "versions": [
                {
                    "version": "8.9.78",
                    "buildVersion": "897800544",
                    "date": "2024-10-02",
                    "size": 80500000,
                    "downloadURL": "https://github.com/whoeevee/EeveeSpotify/releases/download/swift5.3/EeveeSpotify-5.3-8.9.78.ipa",
                    "localizedDescription": "- Aggiunta like dei canzoni alla pagina dell’artista\n- Migliorata l’opzione del reset dei dati (ora cancella anche la libreria e cache)\n- Configurazione scaricata aggiornata; risolti gli arresti anomali dell'app quando si clicca sui tre puntini nella pagina del brano\n- Aggiornato swift-protobuf alla versione 1.28.1 e Swift alla versione 6 (Xcode 16.0)\n- Risolti i crash del tasto Scarica, migliorata la logica di aggancio\n- PetitLyrics è ora disponibile per tutti\n- Aggiustato linguaggio per Cinese semplificato, Cinese tradizionale e Vietnamita"
                },
                {
                    "version": "8.9.76",
                    "buildVersion": "897600516",
                    "date": "2024-09-18T18:27:00+02:00",
                    "size": 77010038,
                    "downloadURL": "https://github.com/whoeevee/EeveeSpotify/releases/download/swift5.2/EeveeSpotify-5.2-8.9.76.ipa",
                    "localizedDescription": "Brazil and french localization updated"
                }
            ],
            "localizedDescription": "This tweak makes Spotify think you have a Premium subscription, granting free listening, just like Spotilife, and provides some additional features like custom lyrics.",
            "iconURL": "https://gocciolafr.github.io/gira/icons/unnamed.png",
            "tintColor": "#1ed760"
        },
        {
            "name": "uYou+ Enhanced",
            "bundleIdentifier": "com.google.ios.youtube",
            "developerName": "arichornlover",
            "subtitle": "Add more features to YouTube",
            "versions": [
                {
                    "version": "19.33.2",
                    "buildVersion": "19.33.2",
                    "date": "2024-05-29",
                    "size": 120400000,
                    "downloadURL": "https://dn720705.ca.archive.org/0/items/YouTubeRebornPlus_19.10.5-4.2.6/yt-uYE-19332-304.ipa",
                    "localizedDescription": "Brazil and french localization updated"
                }
            ],
            "localizedDescription": "uYou is the best tweak for the YouTube app.\n \n uYouEnhanced is a modified version of qnblackcat's uYouPlus & MiRO92's uYou with even more features.\n \n Additional features:\n • Skip sponsorships in videos (iSponsorBlock)\n • Even more PiP options (YouPiP)\n • Unlock 1440p and 2160p resolutions (YTUHD)\n • Disable overlay at the end of videos (YTNoHoverCards)\n • Remove YouTube Premium upsell alerts (NoYTPremium)\n • Enable to Dim the YouTube UI (LowContrastMode)\n • Enable the miniplayer for all videos (YTMiniplayerEnabler)\n • Prevent the notch/Dynamic Island from cutting into 2:1 videos (DontEatMyContent)\n • Configure A/B settings in the YouTube app (YTABConfig)\n • Adds a new button in the Video Player that allows you to copy a url with the ?t=timestamp (YouTimeStamp)\n • And more\n \n More information: \n https://github.com/arichornlover/uYouEnhanced/ \n \n Requires iOS/iPadOS 15.0 or later.\n \n Contributors: qnblackcat, PoomSmart, level3tjg, BandarHelal, galactic, julioverne, Foxster, CokePokes, arichornlover, bhackel and many others. \n\n Credits: MiRO92, HASHBANG, galactic, Lyvendia, ichitaso, Ahmed Bafkir, Tommy Teo, Dayanch96, theos, dodieboy, balackburn and many others.",
            "iconURL": "https://raw.githubusercontent.com/arichornlover/uYouEnhanced/1314354bff6ef07aca60d7b9a77bd91a5f985ab4/Localizations/uYouPlus.bundle/AppIcons/AppIcon4.png",
            "tintColor": "#e81e8a"
        }
    ],

    "news": [
        {
            "title": "Siamo sbarcati su AltStore!",
            "identifier": "1",
            "caption": "Con AltStore potete scaricare le nostre app senza che la Apple blocca le app! Iniziate subito a provarlo scaricando la versione craccata di Spotify, sempre aggiornata!",
            "date": "2024-09-29T23:31:36+02:00",
            "appID": "com.spotify.client",
            "tintColor": "6b89a5",
            "notify": true
        }
    ]
}
